presto/__init__.py
presto/adict.py
presto/asynco.py
presto/handler.py
presto/presto.py
presto/request.py
presto_requests-1.3.6.dist-info/WHEEL
presto_requests-1.3.6.dist-info/METADATA
presto_requests-1.3.6.dist-info/RECORD
