Metadata-Version: 2.1
Name: presto-requests
Version: 1.3.6
Summary: A modern object-oriented HTTP REST client.
Home-page: https://github.com/sitbon/presto
License: AGPLv3
Author: Phillip Sitbon
Author-email: phillip.sitbon@gmail.com
Requires-Python: >=3.11,<4.0
Classifier: Development Status :: 5 - Production/Stable
Classifier: Environment :: Web Environment
Classifier: Intended Audience :: Developers
Classifier: License :: OSI Approved :: GNU Affero General Public License v3 or later (AGPLv3+)
Classifier: License :: Other/Proprietary License
Classifier: Natural Language :: English
Classifier: Operating System :: OS Independent
Classifier: Programming Language :: Python
Classifier: Programming Language :: Python :: 3
Classifier: Programming Language :: Python :: 3.11
Classifier: Programming Language :: Python :: 3
Classifier: Programming Language :: Python :: 3 :: Only
Classifier: Programming Language :: Python :: 3.11
Classifier: Topic :: Internet :: WWW/HTTP
Classifier: Topic :: Software Development :: Libraries
Provides-Extra: async
Requires-Dist: attrdict3 (>=2.0.2,<3.0.0)
Requires-Dist: httpx (>=0.23.3,<0.24.0); extra == "async"
Requires-Dist: requests (>=2.28.2,<3.0.0)
Project-URL: Repository, https://github.com/sitbon/presto
